BIP32.txt
CHANGES
COMMAND-LINE-TOOLS.md
CREDITS
LICENSE
MANIFEST.in
README.md
TESTING.txt
pip-req.txt
setup.py
pycoin/__init__.py
pycoin/block.py
pycoin/bloomfilter.py
pycoin/intbytes.py
pycoin/merkle.py
pycoin/version.py
pycoin/blockchain/BlockChain.py
pycoin/blockchain/ChainFinder.py
pycoin/blockchain/__init__.py
pycoin/cmds/__init__.py
pycoin/cmds/block.py
pycoin/cmds/ku.py
pycoin/cmds/msg.py
pycoin/cmds/tx.py
pycoin/coins/SolutionChecker.py
pycoin/coins/Tx.py
pycoin/coins/TxIn.py
pycoin/coins/TxOut.py
pycoin/coins/__init__.py
pycoin/coins/exceptions.py
pycoin/coins/bcash/Block.py
pycoin/coins/bcash/SolutionChecker.py
pycoin/coins/bcash/Solver.py
pycoin/coins/bcash/Tx.py
pycoin/coins/bcash/__init__.py
pycoin/coins/bgold/SolutionChecker.py
pycoin/coins/bgold/Solver.py
pycoin/coins/bgold/Tx.py
pycoin/coins/bgold/__init__.py
pycoin/coins/bgold/networks.py
pycoin/coins/bitcoin/P2SChecker.py
pycoin/coins/bitcoin/ScriptStreamer.py
pycoin/coins/bitcoin/ScriptTools.py
pycoin/coins/bitcoin/SegwitChecker.py
pycoin/coins/bitcoin/SolutionChecker.py
pycoin/coins/bitcoin/Solver.py
pycoin/coins/bitcoin/Spendable.py
pycoin/coins/bitcoin/Tx.py
pycoin/coins/bitcoin/TxIn.py
pycoin/coins/bitcoin/TxOut.py
pycoin/coins/bitcoin/VM.py
pycoin/coins/bitcoin/__init__.py
pycoin/coins/bitcoin/extras.py
pycoin/coins/bitcoin/make_instruction_lookup.py
pycoin/coins/bitcoin/networks.py
pycoin/coins/litecoin/__init__.py
pycoin/coins/litecoin/networks.py
pycoin/contrib/__init__.py
pycoin/contrib/msg_signing.py
pycoin/contrib/segwit_addr.py
pycoin/contrib/who_signed.py
pycoin/convention/__init__.py
pycoin/convention/tx_fee.py
pycoin/ecdsa/Curve.py
pycoin/ecdsa/Generator.py
pycoin/ecdsa/Point.py
pycoin/ecdsa/__init__.py
pycoin/ecdsa/encrypt.py
pycoin/ecdsa/intstream.py
pycoin/ecdsa/rfc6979.py
pycoin/ecdsa/secp256k1.py
pycoin/ecdsa/secp256r1.py
pycoin/ecdsa/native/__init__.py
pycoin/ecdsa/native/bignum.py
pycoin/ecdsa/native/openssl.py
pycoin/ecdsa/native/secp256k1.py
pycoin/encoding/__init__.py
test_pycoin.egg-info/PKG-INFO
test_pycoin.egg-info/SOURCES.txt
test_pycoin.egg-info/dependency_links.txt
test_pycoin.egg-info/entry_points.txt
test_pycoin.egg-info/top_level.txt