Metadata-Version: 1.1
Name: test-pycoin
Version: 0.90a0
Summary: Fork richard Utilities for Bitcoin and altcoin addresses and transaction manipulation.
Home-page: https://github.com/helenagu01/pycoin
Author: Richard Kiss
Author-email: helen.hk@gmail.com
License: http://opensource.org/licenses/MIT
Platform: UNKNOWN
Classifier: Development Status :: 3 - Alpha
Classifier: Programming Language :: Python :: 2.7
Classifier: Programming Language :: Python :: 3
Classifier: Programming Language :: Python :: 3.5
Classifier: Programming Language :: Python :: 3.6
Classifier: Programming Language :: Python :: 3.7
Classifier: License :: OSI Approved :: MIT License
Classifier: Topic :: Internet
Classifier: Topic :: Security :: Cryptography
Classifier: Topic :: Software Development :: Libraries :: Python Modules
